kosty/__init__.py
kosty/cli.py
kosty/cli/__init__.py
kosty/cli/__main__.py
kosty/cli/apigateway_commands.py
kosty/cli/backup_commands.py
kosty/cli/cloudwatch_commands.py
kosty/cli/dynamodb_commands.py
kosty/cli/ebs_commands.py
kosty/cli/ec2_commands.py
kosty/cli/eip_commands.py
kosty/cli/iam_commands.py
kosty/cli/lambda_commands.py
kosty/cli/lb_commands.py
kosty/cli/nat_commands.py
kosty/cli/rds_commands.py
kosty/cli/route53_commands.py
kosty/cli/s3_commands.py
kosty/cli/sg_commands.py
kosty/cli/snapshots_commands.py
kosty/cli/utils.py
kosty/core/__init__.py
kosty/core/config.py
kosty/core/cost_calculator.py
kosty/core/exceptions.py
kosty/core/executor.py
kosty/core/multi_profile_runner.py
kosty/core/pricing.py
kosty/core/progress.py
kosty/core/reporter.py
kosty/core/scanner.py
kosty/core/storage.py
kosty/core/tag_utils.py
kosty/services/__init__.py
kosty/services/apigateway_audit.py
kosty/services/backup_audit.py
kosty/services/cloudwatch_audit.py
kosty/services/dynamodb_audit.py
kosty/services/ebs_audit.py
kosty/services/ec2_audit.py
kosty/services/eip_audit.py
kosty/services/iam_audit.py
kosty/services/lambda_audit.py
kosty/services/lb_audit.py
kosty/services/nat_audit.py
kosty/services/rds_audit.py
kosty/services/route53_audit.py
kosty/services/s3_audit.py
kosty/services/sg_audit.py
kosty/services/snapshots_audit.py
kosty-1.6.5.dist-info/licenses/LICENSE
kosty-1.6.5.dist-info/METADATA
kosty-1.6.5.dist-info/WHEEL
kosty-1.6.5.dist-info/entry_points.txt
kosty-1.6.5.dist-info/top_level.txt
kosty-1.6.5.dist-info/RECORD
