Metadata-Version: 2.4
Name: kosty
Version: 1.6.5
Summary: AWS Cost Optimization & Security Audit CLI Tool - Identify cost waste, security vulnerabilities, and compliance issues across 16 core AWS services
Home-page: https://github.com/kosty-cloud/kosty
Author: Yassir Kachri
Author-email: Yassir Kachri <yassir@kosty.cloud>
License: MIT License
Project-URL: Homepage, https://github.com/kosty-cloud/kosty
Project-URL: Documentation, https://github.com/kosty-cloud/kosty/blob/main/docs/DOCUMENTATION.md
Project-URL: Repository, https://github.com/kosty-cloud/kosty
Project-URL: Bug Reports, https://github.com/kosty-cloud/kosty/issues
Keywords: aws,cost,optimization,security,audit,cloud,infrastructure,compliance,finops,devops
Classifier: Development Status :: 4 - Beta
Classifier: Intended Audience :: Developers
Classifier: Intended Audience :: System Administrators
Classifier: Topic :: System :: Systems Administration
Classifier: Topic :: Utilities
Classifier: License :: OSI Approved :: MIT License
Classifier: Programming Language :: Python :: 3
Classifier: Programming Language :: Python :: 3.7
Classifier: Programming Language :: Python :: 3.8
Classifier: Programming Language :: Python :: 3.9
Classifier: Programming Language :: Python :: 3.10
Classifier: Programming Language :: Python :: 3.11
Classifier: Operating System :: OS Independent
Requires-Python: >=3.7
License-File: LICENSE
Requires-Dist: click>=8.0.0
Requires-Dist: boto3>=1.26.0
Dynamic: author
Dynamic: home-page
Dynamic: license-file
Dynamic: requires-python
